podfox/__init__.py
podfox-0.1.2.dist-info/DESCRIPTION.rst
podfox-0.1.2.dist-info/METADATA
podfox-0.1.2.dist-info/RECORD
podfox-0.1.2.dist-info/WHEEL
podfox-0.1.2.dist-info/entry_points.txt
podfox-0.1.2.dist-info/metadata.json
podfox-0.1.2.dist-info/top_level.txt
